[{
    "Usename": "atowsie0",
    "Email": "akenzie0@adobe.com",
    "Avatar": "https://robohash.org/animivoluptatibusest.png?size=100x100&set=set1",
    "City": "Wassa-Akropong",
    "DateOfBirth": "1998-12-26T05:26:36Z",
    "Gender": "Male",
    "Introduction": "vestibulum ante ipsum primis in faucibus orci luctus et ultrices posuere cubilia curae donec pharetra magna vestibulum",
    "KnownAs": "Aaron"
  }, {
    "Usename": "csobtka1",
    "Email": "cblewitt1@hp.com",
    "Avatar": "https://robohash.org/autquasieligendi.png?size=100x100&set=set1",
    "City": "Avignon",
    "DateOfBirth": "2001-10-14T12:25:34Z",
    "Gender": "Female",
    "Introduction": "aliquet ultrices erat tortor sollicitudin mi sit amet lobortis sapien sapien non mi integer",
    "KnownAs": "Charlean"
  }, {
    "Usename": "istait2",
    "Email": "iorritt2@chronoengine.com",
    "Avatar": "https://robohash.org/nequeanumquam.png?size=100x100&set=set1",
    "City": "Hupalivka",
    "DateOfBirth": "1991-11-14T21:23:34Z",
    "Gender": "Male",
    "Introduction": "eu orci mauris lacinia sapien quis libero nullam sit amet turpis elementum ligula vehicula consequat morbi",
    "KnownAs": "Irv"
  }, {
    "Usename": "efearey3",
    "Email": "ebrideoke3@ow.ly",
    "Avatar": "https://robohash.org/maioresetqui.png?size=100x100&set=set1",
    "City": "Hubynykha",
    "DateOfBirth": "2007-06-21T22:49:03Z",
    "Gender": "Male",
    "Introduction": "sed sagittis nam congue risus semper porta volutpat quam pede lobortis ligula sit amet eleifend pede libero",
    "KnownAs": "Eddie"
  }, {
    "Usename": "mhamson4",
    "Email": "mskeldinge4@nature.com",
    "Avatar": "https://robohash.org/quasinonet.png?size=100x100&set=set1",
    "City": "Wangmeng",
    "DateOfBirth": "1995-04-30T08:23:02Z",
    "Gender": "Male",
    "Introduction": "suscipit nulla elit ac nulla sed vel enim sit amet nunc",
    "KnownAs": "Maurice"
  }, {
    "Usename": "cturmell5",
    "Email": "cgheorghescu5@plala.or.jp",
    "Avatar": "https://robohash.org/corruptisedconsectetur.png?size=100x100&set=set1",
    "City": "Opechenskiy Posad",
    "DateOfBirth": "2001-03-18T02:03:24Z",
    "Gender": "Male",
    "Introduction": "in congue etiam justo etiam pretium iaculis justo in hac habitasse platea dictumst etiam faucibus",
    "KnownAs": "Christophe"
  }, {
    "Usename": "hletteresse6",
    "Email": "hpatifield6@globo.com",
    "Avatar": "https://robohash.org/cumqueautquidem.png?size=100x100&set=set1",
    "City": "Dalong",
    "DateOfBirth": "1998-10-04T21:33:31Z",
    "Gender": "Female",
    "Introduction": "fusce congue diam id ornare imperdiet sapien urna pretium nisl ut volutpat sapien arcu sed augue",
    "KnownAs": "Hayley"
  }, {
    "Usename": "bbriar7",
    "Email": "bbourdice7@sun.com",
    "Avatar": "https://robohash.org/possimusisteimpedit.png?size=100x100&set=set1",
    "City": "Itapetininga",
    "DateOfBirth": "1992-05-24T16:21:00Z",
    "Gender": "Male",
    "Introduction": "pede lobortis ligula sit amet eleifend pede libero quis orci nullam molestie nibh in lectus pellentesque at",
    "KnownAs": "Brandon"
  }, {
    "Usename": "kroft8",
    "Email": "kberthot8@ustream.tv",
    "Avatar": "https://robohash.org/abpariaturaccusamus.png?size=100x100&set=set1",
    "City": "Chengjiang",
    "DateOfBirth": "2005-12-19T21:38:13Z",
    "Gender": "Male",
    "Introduction": "nisi at nibh in hac habitasse platea dictumst aliquam augue quam sollicitudin vitae consectetuer eget rutrum",
    "KnownAs": "Kelwin"
  }, {
    "Usename": "cpetri9",
    "Email": "ccarman9@nature.com",
    "Avatar": "https://robohash.org/quodsaepearchitecto.png?size=100x100&set=set1",
    "City": "Berezne",
    "DateOfBirth": "1996-08-31T21:47:58Z",
    "Gender": "Male",
    "Introduction": "rhoncus sed vestibulum sit amet cursus id turpis integer aliquet massa id lobortis convallis tortor",
    "KnownAs": "Cosimo"
  }, {
    "Usename": "fpickforda",
    "Email": "fhicka@webnode.com",
    "Avatar": "https://robohash.org/etetsequi.png?size=100x100&set=set1",
    "City": "Södertälje",
    "DateOfBirth": "1996-01-19T03:33:53Z",
    "Gender": "Female",
    "Introduction": "odio donec vitae nisi nam ultrices libero non mattis pulvinar",
    "KnownAs": "Fredra"
  }, {
    "Usename": "gentresb",
    "Email": "gslaughterb@admin.ch",
    "Avatar": "https://robohash.org/insitharum.png?size=100x100&set=set1",
    "City": "San Agustin",
    "DateOfBirth": "1992-03-06T01:08:14Z",
    "Gender": "Female",
    "Introduction": "vivamus metus arcu adipiscing molestie hendrerit at vulputate vitae nisl aenean lectus pellentesque eget nunc donec",
    "KnownAs": "Gilberta"
  }, {
    "Usename": "tcowupc",
    "Email": "tinettc@spiegel.de",
    "Avatar": "https://robohash.org/isteducimusfugit.png?size=100x100&set=set1",
    "City": "Karmaskaly",
    "DateOfBirth": "2010-11-11T10:26:40Z",
    "Gender": "Male",
    "Introduction": "dolor morbi vel lectus in quam fringilla rhoncus mauris enim leo",
    "KnownAs": "Thorvald"
  }, {
    "Usename": "dbroderickd",
    "Email": "damburgyd@ucoz.com",
    "Avatar": "https://robohash.org/utadipisciet.png?size=100x100&set=set1",
    "City": "Nagahama",
    "DateOfBirth": "2006-06-14T22:04:35Z",
    "Gender": "Female",
    "Introduction": "sed tincidunt eu felis fusce posuere felis sed lacus morbi",
    "KnownAs": "Delinda"
  }, {
    "Usename": "foduilleaine",
    "Email": "fkliesle@skype.com",
    "Avatar": "https://robohash.org/facilisautmaxime.png?size=100x100&set=set1",
    "City": "Open Stage",
    "DateOfBirth": "1998-09-27T07:55:01Z",
    "Gender": "Male",
    "Introduction": "tellus nisi eu orci mauris lacinia sapien quis libero nullam",
    "KnownAs": "Falkner"
  }, {
    "Usename": "arogersf",
    "Email": "abrownsettf@usatoday.com",
    "Avatar": "https://robohash.org/modiautfugiat.png?size=100x100&set=set1",
    "City": "Libenge",
    "DateOfBirth": "2005-02-09T12:36:40Z",
    "Gender": "Male",
    "Introduction": "nulla mollis molestie lorem quisque ut erat curabitur gravida nisi at nibh in hac habitasse platea",
    "KnownAs": "Arv"
  }, {
    "Usename": "llosemanng",
    "Email": "lcannong@dagondesign.com",
    "Avatar": "https://robohash.org/delenitiassumendasint.png?size=100x100&set=set1",
    "City": "Sarae",
    "DateOfBirth": "2008-04-04T16:19:32Z",
    "Gender": "Male",
    "Introduction": "sapien dignissim vestibulum vestibulum ante ipsum primis in faucibus orci luctus et ultrices posuere cubilia curae nulla dapibus",
    "KnownAs": "Lorin"
  }, {
    "Usename": "mblaneyh",
    "Email": "msmerdonh@mashable.com",
    "Avatar": "https://robohash.org/sapienteillohic.png?size=100x100&set=set1",
    "City": "Jiangzhang",
    "DateOfBirth": "2000-12-18T16:12:01Z",
    "Gender": "Male",
    "Introduction": "pellentesque quisque porta volutpat erat quisque erat eros viverra eget congue eget semper",
    "KnownAs": "Morgun"
  }, {
    "Usename": "emcneelyi",
    "Email": "eemori@tinypic.com",
    "Avatar": "https://robohash.org/voluptasdelectuseveniet.png?size=100x100&set=set1",
    "City": "Haishan",
    "DateOfBirth": "2009-12-18T07:27:16Z",
    "Gender": "Female",
    "Introduction": "ligula sit amet eleifend pede libero quis orci nullam molestie nibh in lectus pellentesque at nulla suspendisse potenti cras in",
    "KnownAs": "Eugenie"
  }, {
    "Usename": "gpawelj",
    "Email": "gcharnleyj@webs.com",
    "Avatar": "https://robohash.org/nullarecusandaelaboriosam.png?size=100x100&set=set1",
    "City": "Segong",
    "DateOfBirth": "1992-11-11T10:22:29Z",
    "Gender": "Male",
    "Introduction": "felis sed interdum venenatis turpis enim blandit mi in porttitor pede justo eu",
    "KnownAs": "Gardiner"
  }, {
    "Usename": "gsteenk",
    "Email": "gwozencraftk@harvard.edu",
    "Avatar": "https://robohash.org/aspernaturetvoluptates.png?size=100x100&set=set1",
    "City": "Richmond",
    "DateOfBirth": "1998-03-19T07:40:26Z",
    "Gender": "Male",
    "Introduction": "libero quis orci nullam molestie nibh in lectus pellentesque at nulla suspendisse potenti cras",
    "KnownAs": "Gerik"
  }, {
    "Usename": "chankinsl",
    "Email": "ccampbelll@themeforest.net",
    "Avatar": "https://robohash.org/eiusnemorepellat.png?size=100x100&set=set1",
    "City": "Oelaba",
    "DateOfBirth": "2006-07-10T10:09:07Z",
    "Gender": "Male",
    "Introduction": "in hac habitasse platea dictumst maecenas ut massa quis augue luctus",
    "KnownAs": "Cullin"
  }, {
    "Usename": "ogeldardm",
    "Email": "ohullesm@fema.gov",
    "Avatar": "https://robohash.org/dignissimoseossint.png?size=100x100&set=set1",
    "City": "Firminópolis",
    "DateOfBirth": "1997-02-18T18:32:49Z",
    "Gender": "Male",
    "Introduction": "nascetur ridiculus mus etiam vel augue vestibulum rutrum rutrum neque aenean auctor gravida sem",
    "KnownAs": "Oliver"
  }, {
    "Usename": "amcgawnn",
    "Email": "ageron@weebly.com",
    "Avatar": "https://robohash.org/cumquevoluptatesodio.png?size=100x100&set=set1",
    "City": "Yinjiaxi",
    "DateOfBirth": "2005-06-10T07:35:31Z",
    "Gender": "Male",
    "Introduction": "orci vehicula condimentum curabitur in libero ut massa volutpat convallis morbi odio odio elementum eu interdum",
    "KnownAs": "Allister"
  }, {
    "Usename": "agaulto",
    "Email": "adonavano@mail.ru",
    "Avatar": "https://robohash.org/minusintempore.png?size=100x100&set=set1",
    "City": "Xiaojia",
    "DateOfBirth": "1992-03-31T14:11:58Z",
    "Gender": "Female",
    "Introduction": "quam suspendisse potenti nullam porttitor lacus at turpis donec posuere metus vitae ipsum",
    "KnownAs": "Alvira"
  }, {
    "Usename": "tthundercliffep",
    "Email": "tkezarp@yahoo.co.jp",
    "Avatar": "https://robohash.org/iustosimiliqueex.png?size=100x100&set=set1",
    "City": "Karangkeng",
    "DateOfBirth": "2004-12-03T19:43:19Z",
    "Gender": "Female",
    "Introduction": "tortor sollicitudin mi sit amet lobortis sapien sapien non mi integer ac neque duis",
    "KnownAs": "Tawnya"
  }, {
    "Usename": "amassinghamq",
    "Email": "akillingbackq@unblog.fr",
    "Avatar": "https://robohash.org/dolorevitaedolores.png?size=100x100&set=set1",
    "City": "Allen",
    "DateOfBirth": "2007-11-30T16:37:38Z",
    "Gender": "Male",
    "Introduction": "augue vestibulum rutrum rutrum neque aenean auctor gravida sem praesent id massa id",
    "KnownAs": "Abbot"
  }, {
    "Usename": "cbunfordr",
    "Email": "cblondeller@miibeian.gov.cn",
    "Avatar": "https://robohash.org/temporeexdolorem.png?size=100x100&set=set1",
    "City": "Liwonde",
    "DateOfBirth": "2007-07-24T15:21:38Z",
    "Gender": "Female",
    "Introduction": "vivamus metus arcu adipiscing molestie hendrerit at vulputate vitae nisl aenean lectus pellentesque eget nunc",
    "KnownAs": "Claudine"
  }, {
    "Usename": "cradsdales",
    "Email": "cpetheridges@japanpost.jp",
    "Avatar": "https://robohash.org/undeetnostrum.png?size=100x100&set=set1",
    "City": "Yeshan",
    "DateOfBirth": "2002-02-07T12:14:04Z",
    "Gender": "Male",
    "Introduction": "faucibus cursus urna ut tellus nulla ut erat id mauris vulputate elementum",
    "KnownAs": "Christos"
  }, {
    "Usename": "htasselert",
    "Email": "hprynnet@biblegateway.com",
    "Avatar": "https://robohash.org/indeseruntat.png?size=100x100&set=set1",
    "City": "Cholargós",
    "DateOfBirth": "2004-12-04T01:17:08Z",
    "Gender": "Female",
    "Introduction": "eros elementum pellentesque quisque porta volutpat erat quisque erat eros viverra eget congue",
    "KnownAs": "Harmonie"
  }, {
    "Usename": "bstarzakeru",
    "Email": "bdyshartu@networkadvertising.org",
    "Avatar": "https://robohash.org/dictasuntnesciunt.png?size=100x100&set=set1",
    "City": "Kasturi",
    "DateOfBirth": "2002-10-03T05:38:34Z",
    "Gender": "Male",
    "Introduction": "lacus curabitur at ipsum ac tellus semper interdum mauris ullamcorper purus sit amet nulla",
    "KnownAs": "Bruce"
  }, {
    "Usename": "wbernasekv",
    "Email": "wcutforthv@ft.com",
    "Avatar": "https://robohash.org/ipsumnobisrerum.png?size=100x100&set=set1",
    "City": "Bruxelles",
    "DateOfBirth": "2000-02-05T00:43:05Z",
    "Gender": "Male",
    "Introduction": "nulla justo aliquam quis turpis eget elit sodales scelerisque mauris sit amet eros",
    "KnownAs": "Wesley"
  }, {
    "Usename": "tshoryw",
    "Email": "tsterlingw@fastcompany.com",
    "Avatar": "https://robohash.org/mollitiaipsamsit.png?size=100x100&set=set1",
    "City": "Hanamaki",
    "DateOfBirth": "2005-09-15T13:36:24Z",
    "Gender": "Male",
    "Introduction": "ac est lacinia nisi venenatis tristique fusce congue diam id ornare imperdiet sapien urna pretium nisl",
    "KnownAs": "Torrence"
  }, {
    "Usename": "dmcdonaldx",
    "Email": "dolearyx@surveymonkey.com",
    "Avatar": "https://robohash.org/distinctiosolutaeaque.png?size=100x100&set=set1",
    "City": "Turochak",
    "DateOfBirth": "1994-07-06T01:18:06Z",
    "Gender": "Female",
    "Introduction": "morbi non lectus aliquam sit amet diam in magna bibendum imperdiet nullam orci",
    "KnownAs": "Deva"
  }, {
    "Usename": "tfuchery",
    "Email": "tbeckworthy@usa.gov",
    "Avatar": "https://robohash.org/nemosequimaxime.png?size=100x100&set=set1",
    "City": "Pavia",
    "DateOfBirth": "1994-08-21T00:10:26Z",
    "Gender": "Female",
    "Introduction": "et magnis dis parturient montes nascetur ridiculus mus etiam vel augue vestibulum rutrum rutrum neque aenean auctor gravida sem praesent",
    "KnownAs": "Tiffie"
  }, {
    "Usename": "msimecekz",
    "Email": "mwollenz@trellian.com",
    "Avatar": "https://robohash.org/officiaarchitectoodit.png?size=100x100&set=set1",
    "City": "Conel",
    "DateOfBirth": "2000-01-03T11:39:14Z",
    "Gender": "Female",
    "Introduction": "ipsum primis in faucibus orci luctus et ultrices posuere cubilia",
    "KnownAs": "Marjorie"
  }, {
    "Usename": "hthal10",
    "Email": "hclappson10@wordpress.com",
    "Avatar": "https://robohash.org/quaehicest.png?size=100x100&set=set1",
    "City": "San José",
    "DateOfBirth": "1992-03-23T17:45:49Z",
    "Gender": "Male",
    "Introduction": "tortor quis turpis sed ante vivamus tortor duis mattis egestas metus aenean fermentum donec ut mauris eget massa",
    "KnownAs": "Hayyim"
  }, {
    "Usename": "stunnacliffe11",
    "Email": "sfilyushkin11@omniture.com",
    "Avatar": "https://robohash.org/ipsumquiaaut.png?size=100x100&set=set1",
    "City": "Al Funayţīs",
    "DateOfBirth": "2003-08-06T13:55:26Z",
    "Gender": "Female",
    "Introduction": "a ipsum integer a nibh in quis justo maecenas rhoncus aliquam lacus morbi quis tortor id nulla ultrices aliquet maecenas",
    "KnownAs": "Sherye"
  }, {
    "Usename": "asharma12",
    "Email": "amcgeachy12@macromedia.com",
    "Avatar": "https://robohash.org/remdolorumblanditiis.png?size=100x100&set=set1",
    "City": "Sicheng",
    "DateOfBirth": "1990-03-26T10:41:26Z",
    "Gender": "Male",
    "Introduction": "blandit nam nulla integer pede justo lacinia eget tincidunt eget",
    "KnownAs": "Andrew"
  }, {
    "Usename": "cweatherhogg13",
    "Email": "cmathelon13@histats.com",
    "Avatar": "https://robohash.org/inventoreaperiamconsectetur.png?size=100x100&set=set1",
    "City": "Norwalk",
    "DateOfBirth": "1993-06-01T14:34:20Z",
    "Gender": "Female",
    "Introduction": "sed vel enim sit amet nunc viverra dapibus nulla suscipit ligula in lacus",
    "KnownAs": "Caralie"
  }, {
    "Usename": "fducastel14",
    "Email": "fderrington14@jugem.jp",
    "Avatar": "https://robohash.org/quiofficiislibero.png?size=100x100&set=set1",
    "City": "Leninskiy",
    "DateOfBirth": "2009-05-03T02:28:48Z",
    "Gender": "Male",
    "Introduction": "morbi sem mauris laoreet ut rhoncus aliquet pulvinar sed nisl nunc",
    "KnownAs": "Fonsie"
  }, {
    "Usename": "cridhole15",
    "Email": "cmanuel15@yellowbook.com",
    "Avatar": "https://robohash.org/quosnonfacere.png?size=100x100&set=set1",
    "City": "Ti-n-Essako",
    "DateOfBirth": "1994-03-21T06:49:11Z",
    "Gender": "Male",
    "Introduction": "nisl aenean lectus pellentesque eget nunc donec quis orci eget orci vehicula condimentum curabitur in",
    "KnownAs": "Crawford"
  }, {
    "Usename": "psynnot16",
    "Email": "pgerdes16@hp.com",
    "Avatar": "https://robohash.org/voluptasdeseruntvoluptates.png?size=100x100&set=set1",
    "City": "Santa Catalina",
    "DateOfBirth": "1991-04-03T10:24:44Z",
    "Gender": "Male",
    "Introduction": "sed justo pellentesque viverra pede ac diam cras pellentesque volutpat dui maecenas tristique est et tempus",
    "KnownAs": "Pip"
  }, {
    "Usename": "nandroletti17",
    "Email": "nmarzella17@tripod.com",
    "Avatar": "https://robohash.org/estvoluptatibussit.png?size=100x100&set=set1",
    "City": "Adani",
    "DateOfBirth": "2007-09-05T14:39:23Z",
    "Gender": "Female",
    "Introduction": "dui maecenas tristique est et tempus semper est quam pharetra magna ac consequat metus sapien ut nunc",
    "KnownAs": "Nikki"
  }, {
    "Usename": "pfurmston18",
    "Email": "pguthrie18@sfgate.com",
    "Avatar": "https://robohash.org/magniipsumquasi.png?size=100x100&set=set1",
    "City": "Sedinginan",
    "DateOfBirth": "1991-06-26T01:25:35Z",
    "Gender": "Female",
    "Introduction": "libero ut massa volutpat convallis morbi odio odio elementum eu interdum eu tincidunt in leo maecenas pulvinar",
    "KnownAs": "Peria"
  }, {
    "Usename": "eeckly19",
    "Email": "edewilde19@dailymotion.com",
    "Avatar": "https://robohash.org/recusandaeeosquia.png?size=100x100&set=set1",
    "City": "Florida",
    "DateOfBirth": "1999-04-08T10:54:19Z",
    "Gender": "Female",
    "Introduction": "nisi nam ultrices libero non mattis pulvinar nulla pede ullamcorper",
    "KnownAs": "Emilie"
  }, {
    "Usename": "asurgen1a",
    "Email": "abroomer1a@wordpress.com",
    "Avatar": "https://robohash.org/repellatdoloremquefugiat.png?size=100x100&set=set1",
    "City": "Dawuhan",
    "DateOfBirth": "2010-05-25T03:32:14Z",
    "Gender": "Female",
    "Introduction": "ut nunc vestibulum ante ipsum primis in faucibus orci luctus et ultrices posuere cubilia curae mauris viverra diam vitae",
    "KnownAs": "Angil"
  }, {
    "Usename": "sfishleigh1b",
    "Email": "sesherwood1b@boston.com",
    "Avatar": "https://robohash.org/undeetquis.png?size=100x100&set=set1",
    "City": "Wendo",
    "DateOfBirth": "2000-02-16T01:45:39Z",
    "Gender": "Female",
    "Introduction": "nec dui luctus rutrum nulla tellus in sagittis dui vel nisl duis ac nibh fusce lacus",
    "KnownAs": "Shanon"
  }, {
    "Usename": "kmcevay1c",
    "Email": "kbentame1c@pagesperso-orange.fr",
    "Avatar": "https://robohash.org/debitisnobisconsectetur.png?size=100x100&set=set1",
    "City": "Aurora",
    "DateOfBirth": "2006-10-09T22:30:27Z",
    "Gender": "Female",
    "Introduction": "urna pretium nisl ut volutpat sapien arcu sed augue aliquam erat volutpat in congue etiam",
    "KnownAs": "Kordula"
  }, {
    "Usename": "ogaitley1d",
    "Email": "orogerson1d@yandex.ru",
    "Avatar": "https://robohash.org/voluptasquiullam.png?size=100x100&set=set1",
    "City": "Huzhen",
    "DateOfBirth": "1995-05-04T07:04:47Z",
    "Gender": "Male",
    "Introduction": "odio condimentum id luctus nec molestie sed justo pellentesque viverra pede ac diam cras",
    "KnownAs": "Obed"
  }, {
    "Usename": "kmacardle1e",
    "Email": "kberkeley1e@nih.gov",
    "Avatar": "https://robohash.org/magnamnihilaut.png?size=100x100&set=set1",
    "City": "Zhouyuan",
    "DateOfBirth": "1994-04-04T13:05:54Z",
    "Gender": "Female",
    "Introduction": "nulla suspendisse potenti cras in purus eu magna vulputate luctus cum sociis natoque penatibus et magnis dis parturient montes nascetur",
    "KnownAs": "Kalila"
  }, {
    "Usename": "mlougheed1f",
    "Email": "mmcnally1f@thetimes.co.uk",
    "Avatar": "https://robohash.org/inestexplicabo.png?size=100x100&set=set1",
    "City": "Haninge",
    "DateOfBirth": "1993-12-04T23:46:09Z",
    "Gender": "Female",
    "Introduction": "cubilia curae donec pharetra magna vestibulum aliquet ultrices erat tortor sollicitudin mi sit",
    "KnownAs": "Maxine"
  }, {
    "Usename": "gsibborn1g",
    "Email": "gdingsdale1g@google.co.uk",
    "Avatar": "https://robohash.org/impeditblanditiisnulla.png?size=100x100&set=set1",
    "City": "Yemva",
    "DateOfBirth": "2003-11-20T09:16:32Z",
    "Gender": "Female",
    "Introduction": "phasellus in felis donec semper sapien a libero nam dui proin leo odio porttitor id",
    "KnownAs": "Glenine"
  }, {
    "Usename": "dcartledge1h",
    "Email": "dandraud1h@indiatimes.com",
    "Avatar": "https://robohash.org/veniamnequedeleniti.png?size=100x100&set=set1",
    "City": "Viking",
    "DateOfBirth": "1990-12-28T02:07:51Z",
    "Gender": "Male",
    "Introduction": "velit vivamus vel nulla eget eros elementum pellentesque quisque porta volutpat erat quisque erat eros viverra eget congue",
    "KnownAs": "Denney"
  }, {
    "Usename": "skift1i",
    "Email": "sparken1i@printfriendly.com",
    "Avatar": "https://robohash.org/officiisvelitquidem.png?size=100x100&set=set1",
    "City": "Néos Mylótopos",
    "DateOfBirth": "2002-08-11T17:12:24Z",
    "Gender": "Male",
    "Introduction": "nisl duis bibendum felis sed interdum venenatis turpis enim blandit mi in porttitor pede justo eu massa donec dapibus duis",
    "KnownAs": "Sinclair"
  }, {
    "Usename": "areyes1j",
    "Email": "acharke1j@moonfruit.com",
    "Avatar": "https://robohash.org/adipiscietvoluptates.png?size=100x100&set=set1",
    "City": "Strogino",
    "DateOfBirth": "2003-01-31T14:18:17Z",
    "Gender": "Female",
    "Introduction": "nibh quisque id justo sit amet sapien dignissim vestibulum vestibulum ante ipsum primis in faucibus orci luctus",
    "KnownAs": "Ali"
  }, {
    "Usename": "jnoone1k",
    "Email": "jgurnee1k@bluehost.com",
    "Avatar": "https://robohash.org/sitametab.png?size=100x100&set=set1",
    "City": "Kidangbang",
    "DateOfBirth": "2002-01-10T06:53:53Z",
    "Gender": "Female",
    "Introduction": "nibh in hac habitasse platea dictumst aliquam augue quam sollicitudin vitae consectetuer eget rutrum at",
    "KnownAs": "Jesse"
  }, {
    "Usename": "mrubke1l",
    "Email": "mabbe1l@japanpost.jp",
    "Avatar": "https://robohash.org/rerumetnon.png?size=100x100&set=set1",
    "City": "Solosolo",
    "DateOfBirth": "1990-03-10T19:10:00Z",
    "Gender": "Female",
    "Introduction": "aliquam non mauris morbi non lectus aliquam sit amet diam in magna bibendum imperdiet nullam",
    "KnownAs": "Melisandra"
  }, {
    "Usename": "jallicock1m",
    "Email": "jdrain1m@uol.com.br",
    "Avatar": "https://robohash.org/repellendusarchitectoest.png?size=100x100&set=set1",
    "City": "Chinchaypujio",
    "DateOfBirth": "1997-05-31T07:48:08Z",
    "Gender": "Male",
    "Introduction": "maecenas leo odio condimentum id luctus nec molestie sed justo pellentesque",
    "KnownAs": "Jamesy"
  }, {
    "Usename": "ckenaway1n",
    "Email": "cfrosdick1n@netscape.com",
    "Avatar": "https://robohash.org/aharumveritatis.png?size=100x100&set=set1",
    "City": "Tamanan",
    "DateOfBirth": "1990-07-03T02:34:02Z",
    "Gender": "Male",
    "Introduction": "augue aliquam erat volutpat in congue etiam justo etiam pretium iaculis justo in hac habitasse platea dictumst etiam faucibus",
    "KnownAs": "Chick"
  }, {
    "Usename": "crabbitts1o",
    "Email": "chardypiggin1o@theglobeandmail.com",
    "Avatar": "https://robohash.org/nequeetaut.png?size=100x100&set=set1",
    "City": "Panbang",
    "DateOfBirth": "2002-08-24T04:15:16Z",
    "Gender": "Female",
    "Introduction": "a pede posuere nonummy integer non velit donec diam neque vestibulum eget vulputate ut ultrices vel augue vestibulum ante",
    "KnownAs": "Cookie"
  }, {
    "Usename": "lsandwith1p",
    "Email": "lkirsche1p@hhs.gov",
    "Avatar": "https://robohash.org/etadipisciut.png?size=100x100&set=set1",
    "City": "Ungsang",
    "DateOfBirth": "2003-12-22T19:35:43Z",
    "Gender": "Female",
    "Introduction": "ante vivamus tortor duis mattis egestas metus aenean fermentum donec ut mauris eget massa",
    "KnownAs": "Loleta"
  }, {
    "Usename": "dseaborne1q",
    "Email": "dlanfranchi1q@gizmodo.com",
    "Avatar": "https://robohash.org/laboriosamliberoet.png?size=100x100&set=set1",
    "City": "Emnambithi-Ladysmith",
    "DateOfBirth": "2000-03-10T00:16:47Z",
    "Gender": "Male",
    "Introduction": "dolor vel est donec odio justo sollicitudin ut suscipit a feugiat et eros vestibulum ac est lacinia nisi venenatis tristique",
    "KnownAs": "Dunc"
  }, {
    "Usename": "eallchorne1r",
    "Email": "etopaz1r@typepad.com",
    "Avatar": "https://robohash.org/consequunturomnisconsequatur.png?size=100x100&set=set1",
    "City": "Jasionów",
    "DateOfBirth": "2007-03-25T04:06:52Z",
    "Gender": "Male",
    "Introduction": "eu massa donec dapibus duis at velit eu est congue elementum in hac",
    "KnownAs": "Ethelred"
  }, {
    "Usename": "fbrabban1s",
    "Email": "fthomassen1s@zdnet.com",
    "Avatar": "https://robohash.org/etnecessitatibusperspiciatis.png?size=100x100&set=set1",
    "City": "Gawul",
    "DateOfBirth": "1993-07-13T18:21:40Z",
    "Gender": "Male",
    "Introduction": "convallis eget eleifend luctus ultricies eu nibh quisque id justo sit amet sapien dignissim vestibulum vestibulum",
    "KnownAs": "Farris"
  }, {
    "Usename": "tgeraldez1t",
    "Email": "tleleu1t@npr.org",
    "Avatar": "https://robohash.org/praesentiumdoloremexplicabo.png?size=100x100&set=set1",
    "City": "Calamba",
    "DateOfBirth": "2003-08-03T07:30:34Z",
    "Gender": "Male",
    "Introduction": "justo sollicitudin ut suscipit a feugiat et eros vestibulum ac est lacinia nisi venenatis",
    "KnownAs": "Templeton"
  }, {
    "Usename": "jpeacher1u",
    "Email": "jdalla1u@bluehost.com",
    "Avatar": "https://robohash.org/assumendaeaperspiciatis.png?size=100x100&set=set1",
    "City": "Malaryta",
    "DateOfBirth": "2004-09-15T00:36:17Z",
    "Gender": "Female",
    "Introduction": "quis odio consequat varius integer ac leo pellentesque ultrices mattis",
    "KnownAs": "Jelene"
  }, {
    "Usename": "pduckett1v",
    "Email": "pchasmar1v@unesco.org",
    "Avatar": "https://robohash.org/estaspernaturillum.png?size=100x100&set=set1",
    "City": "Krivodanovka",
    "DateOfBirth": "2009-07-29T09:50:56Z",
    "Gender": "Female",
    "Introduction": "enim lorem ipsum dolor sit amet consectetuer adipiscing elit proin interdum mauris non",
    "KnownAs": "Patrica"
  }, {
    "Usename": "rmasser1w",
    "Email": "rconcannon1w@state.gov",
    "Avatar": "https://robohash.org/velitsintomnis.png?size=100x100&set=set1",
    "City": "Lishu",
    "DateOfBirth": "1999-04-07T18:15:06Z",
    "Gender": "Female",
    "Introduction": "ipsum primis in faucibus orci luctus et ultrices posuere cubilia curae duis",
    "KnownAs": "Roanne"
  }, {
    "Usename": "nmea1x",
    "Email": "nredley1x@wordpress.org",
    "Avatar": "https://robohash.org/undeblanditiiscum.png?size=100x100&set=set1",
    "City": "Yanglinwei",
    "DateOfBirth": "1994-06-05T02:36:49Z",
    "Gender": "Male",
    "Introduction": "vestibulum ante ipsum primis in faucibus orci luctus et ultrices posuere",
    "KnownAs": "Neill"
  }, {
    "Usename": "dshewry1y",
    "Email": "dkuschek1y@odnoklassniki.ru",
    "Avatar": "https://robohash.org/providenteligendiesse.png?size=100x100&set=set1",
    "City": "Namibe",
    "DateOfBirth": "2009-07-07T22:51:42Z",
    "Gender": "Male",
    "Introduction": "nulla suspendisse potenti cras in purus eu magna vulputate luctus cum sociis natoque",
    "KnownAs": "Dennet"
  }, {
    "Usename": "pyves1z",
    "Email": "pbordes1z@cbslocal.com",
    "Avatar": "https://robohash.org/placeatquivoluptatum.png?size=100x100&set=set1",
    "City": "Caibiran",
    "DateOfBirth": "1998-02-16T02:00:10Z",
    "Gender": "Female",
    "Introduction": "eros suspendisse accumsan tortor quis turpis sed ante vivamus tortor duis mattis egestas metus",
    "KnownAs": "Persis"
  }, {
    "Usename": "mmansuer20",
    "Email": "mlorenz20@facebook.com",
    "Avatar": "https://robohash.org/cupiditatealiquamaut.png?size=100x100&set=set1",
    "City": "Pepe",
    "DateOfBirth": "2005-01-24T20:24:05Z",
    "Gender": "Male",
    "Introduction": "varius ut blandit non interdum in ante vestibulum ante ipsum primis in faucibus orci luctus",
    "KnownAs": "Mattias"
  }, {
    "Usename": "wsomers21",
    "Email": "wmordey21@simplemachines.org",
    "Avatar": "https://robohash.org/odioetet.png?size=100x100&set=set1",
    "City": "Bang Ban",
    "DateOfBirth": "2001-05-16T03:54:09Z",
    "Gender": "Male",
    "Introduction": "orci luctus et ultrices posuere cubilia curae nulla dapibus dolor vel",
    "KnownAs": "Winslow"
  }, {
    "Usename": "oleavey22",
    "Email": "oeddie22@squidoo.com",
    "Avatar": "https://robohash.org/suntreprehenderitveniam.png?size=100x100&set=set1",
    "City": "Perepravnaya",
    "DateOfBirth": "1990-07-27T03:42:28Z",
    "Gender": "Male",
    "Introduction": "maecenas ut massa quis augue luctus tincidunt nulla mollis molestie lorem quisque ut erat",
    "KnownAs": "Oby"
  }, {
    "Usename": "rgrealey23",
    "Email": "rkenset23@newyorker.com",
    "Avatar": "https://robohash.org/distinctioomnisinventore.png?size=100x100&set=set1",
    "City": "Neiguan",
    "DateOfBirth": "1992-05-02T11:34:22Z",
    "Gender": "Female",
    "Introduction": "eget congue eget semper rutrum nulla nunc purus phasellus in felis donec semper sapien a libero nam dui proin",
    "KnownAs": "Retha"
  }, {
    "Usename": "tspellard24",
    "Email": "tcrommett24@plala.or.jp",
    "Avatar": "https://robohash.org/doloribusautemsoluta.png?size=100x100&set=set1",
    "City": "Baytā al Fawqā",
    "DateOfBirth": "1994-10-31T02:33:16Z",
    "Gender": "Male",
    "Introduction": "risus auctor sed tristique in tempus sit amet sem fusce consequat nulla nisl nunc",
    "KnownAs": "Tedd"
  }, {
    "Usename": "awelbrock25",
    "Email": "amoynihan25@blogspot.com",
    "Avatar": "https://robohash.org/nihilcumqueratione.png?size=100x100&set=set1",
    "City": "Sankwia",
    "DateOfBirth": "1996-10-05T08:36:10Z",
    "Gender": "Male",
    "Introduction": "in sapien iaculis congue vivamus metus arcu adipiscing molestie hendrerit at vulputate vitae nisl aenean lectus pellentesque eget",
    "KnownAs": "Arie"
  }, {
    "Usename": "gchittem26",
    "Email": "gscholler26@hud.gov",
    "Avatar": "https://robohash.org/laudantiummagniquidem.png?size=100x100&set=set1",
    "City": "Jifeng",
    "DateOfBirth": "2001-04-08T22:08:57Z",
    "Gender": "Female",
    "Introduction": "lectus suspendisse potenti in eleifend quam a odio in hac habitasse platea dictumst maecenas",
    "KnownAs": "Gretta"
  }, {
    "Usename": "lcampana27",
    "Email": "lcromett27@jigsy.com",
    "Avatar": "https://robohash.org/reiciendisfugarepellat.png?size=100x100&set=set1",
    "City": "Maji",
    "DateOfBirth": "1995-07-21T05:07:43Z",
    "Gender": "Male",
    "Introduction": "dapibus duis at velit eu est congue elementum in hac habitasse platea dictumst morbi vestibulum velit id pretium iaculis diam",
    "KnownAs": "Land"
  }, {
    "Usename": "emccutheon28",
    "Email": "elindenman28@boston.com",
    "Avatar": "https://robohash.org/explicaboametdoloremque.png?size=100x100&set=set1",
    "City": "Kulevcha",
    "DateOfBirth": "2004-05-26T02:47:59Z",
    "Gender": "Female",
    "Introduction": "sapien urna pretium nisl ut volutpat sapien arcu sed augue aliquam erat volutpat in congue etiam justo etiam pretium",
    "KnownAs": "Eadith"
  }, {
    "Usename": "sstockill29",
    "Email": "swinslow29@wufoo.com",
    "Avatar": "https://robohash.org/magniutmagnam.png?size=100x100&set=set1",
    "City": "Pevek",
    "DateOfBirth": "2005-09-14T13:44:51Z",
    "Gender": "Female",
    "Introduction": "venenatis lacinia aenean sit amet justo morbi ut odio cras mi pede malesuada in imperdiet et commodo vulputate",
    "KnownAs": "Sophey"
  }, {
    "Usename": "jventris2a",
    "Email": "jkilcullen2a@bizjournals.com",
    "Avatar": "https://robohash.org/molestiascumofficia.png?size=100x100&set=set1",
    "City": "Cavinti",
    "DateOfBirth": "2004-09-24T06:00:30Z",
    "Gender": "Female",
    "Introduction": "sit amet eros suspendisse accumsan tortor quis turpis sed ante vivamus tortor duis mattis egestas metus aenean fermentum donec",
    "KnownAs": "Janifer"
  }, {
    "Usename": "rferns2b",
    "Email": "rjesper2b@jimdo.com",
    "Avatar": "https://robohash.org/estimpedita.png?size=100x100&set=set1",
    "City": "São Martinho do Campo",
    "DateOfBirth": "1999-06-22T04:11:17Z",
    "Gender": "Female",
    "Introduction": "mauris ullamcorper purus sit amet nulla quisque arcu libero rutrum",
    "KnownAs": "Reeta"
  }, {
    "Usename": "rrobbel2c",
    "Email": "rkennerley2c@desdev.cn",
    "Avatar": "https://robohash.org/rerumhicsapiente.png?size=100x100&set=set1",
    "City": "Karang",
    "DateOfBirth": "1999-05-13T13:13:11Z",
    "Gender": "Male",
    "Introduction": "at vulputate vitae nisl aenean lectus pellentesque eget nunc donec quis orci eget orci vehicula condimentum curabitur",
    "KnownAs": "Reade"
  }, {
    "Usename": "ucamden2d",
    "Email": "ubreffitt2d@histats.com",
    "Avatar": "https://robohash.org/estliberovoluptas.png?size=100x100&set=set1",
    "City": "Xinfu",
    "DateOfBirth": "2008-08-13T20:48:14Z",
    "Gender": "Male",
    "Introduction": "interdum mauris non ligula pellentesque ultrices phasellus id sapien in sapien iaculis congue",
    "KnownAs": "Ulrich"
  }, {
    "Usename": "yjewess2e",
    "Email": "yjodrellec2e@usnews.com",
    "Avatar": "https://robohash.org/blanditiisminussunt.png?size=100x100&set=set1",
    "City": "Duifang",
    "DateOfBirth": "2009-10-06T08:10:35Z",
    "Gender": "Male",
    "Introduction": "congue risus semper porta volutpat quam pede lobortis ligula sit amet eleifend pede libero",
    "KnownAs": "Yvor"
  }, {
    "Usename": "ogorce2f",
    "Email": "obreming2f@newyorker.com",
    "Avatar": "https://robohash.org/commodinequeest.png?size=100x100&set=set1",
    "City": "Riversdale",
    "DateOfBirth": "1991-12-02T16:34:19Z",
    "Gender": "Female",
    "Introduction": "viverra eget congue eget semper rutrum nulla nunc purus phasellus in felis donec",
    "KnownAs": "Oralia"
  }, {
    "Usename": "sdummer2g",
    "Email": "scadd2g@cornell.edu",
    "Avatar": "https://robohash.org/eteanam.png?size=100x100&set=set1",
    "City": "Muzambinho",
    "DateOfBirth": "2001-03-31T14:48:13Z",
    "Gender": "Male",
    "Introduction": "libero convallis eget eleifend luctus ultricies eu nibh quisque id justo sit amet",
    "KnownAs": "Scott"
  }, {
    "Usename": "jodrought2h",
    "Email": "jcosson2h@gnu.org",
    "Avatar": "https://robohash.org/accusantiumconsequaturnisi.png?size=100x100&set=set1",
    "City": "Jiading",
    "DateOfBirth": "1992-09-10T04:16:58Z",
    "Gender": "Male",
    "Introduction": "accumsan tellus nisi eu orci mauris lacinia sapien quis libero nullam sit amet",
    "KnownAs": "Jarid"
  }, {
    "Usename": "abradley2i",
    "Email": "abooty2i@slashdot.org",
    "Avatar": "https://robohash.org/utblanditiisquisquam.png?size=100x100&set=set1",
    "City": "Sidamulya Satu",
    "DateOfBirth": "1999-11-29T08:27:05Z",
    "Gender": "Male",
    "Introduction": "odio porttitor id consequat in consequat ut nulla sed accumsan felis ut at dolor",
    "KnownAs": "Arnold"
  }, {
    "Usename": "lblazi2j",
    "Email": "lborder2j@e-recht24.de",
    "Avatar": "https://robohash.org/voluptatemeumimpedit.png?size=100x100&set=set1",
    "City": "Carhuamayo",
    "DateOfBirth": "1991-12-24T18:58:55Z",
    "Gender": "Female",
    "Introduction": "lobortis est phasellus sit amet erat nulla tempus vivamus in felis eu sapien cursus vestibulum proin eu mi",
    "KnownAs": "Lynnett"
  }, {
    "Usename": "lsedman2k",
    "Email": "llarner2k@tuttocitta.it",
    "Avatar": "https://robohash.org/aperiamutdolores.png?size=100x100&set=set1",
    "City": "Jarānwāla",
    "DateOfBirth": "2005-08-08T06:11:38Z",
    "Gender": "Female",
    "Introduction": "porttitor pede justo eu massa donec dapibus duis at velit eu est congue elementum in hac habitasse platea dictumst morbi",
    "KnownAs": "Lorilyn"
  }, {
    "Usename": "etorry2l",
    "Email": "estanman2l@myspace.com",
    "Avatar": "https://robohash.org/quaeratatadipisci.png?size=100x100&set=set1",
    "City": "Kampungladang",
    "DateOfBirth": "2001-02-18T08:13:54Z",
    "Gender": "Female",
    "Introduction": "felis sed lacus morbi sem mauris laoreet ut rhoncus aliquet pulvinar sed nisl nunc rhoncus dui vel sem sed sagittis",
    "KnownAs": "Esta"
  }, {
    "Usename": "bdrivers2m",
    "Email": "byaknov2m@icio.us",
    "Avatar": "https://robohash.org/minusvoluptatefacilis.png?size=100x100&set=set1",
    "City": "Motala",
    "DateOfBirth": "1991-04-28T11:09:53Z",
    "Gender": "Male",
    "Introduction": "ut erat id mauris vulputate elementum nullam varius nulla facilisi cras non velit nec",
    "KnownAs": "Barth"
  }, {
    "Usename": "bogglebie2n",
    "Email": "bbordes2n@stumbleupon.com",
    "Avatar": "https://robohash.org/harumaperiamofficia.png?size=100x100&set=set1",
    "City": "Frankfort",
    "DateOfBirth": "1999-10-15T09:20:57Z",
    "Gender": "Male",
    "Introduction": "lorem quisque ut erat curabitur gravida nisi at nibh in hac habitasse platea dictumst aliquam augue quam sollicitudin vitae",
    "KnownAs": "Benton"
  }, {
    "Usename": "asivewright2o",
    "Email": "amccroft2o@histats.com",
    "Avatar": "https://robohash.org/autetea.png?size=100x100&set=set1",
    "City": "P’yŏngsŏng",
    "DateOfBirth": "2001-04-22T18:31:32Z",
    "Gender": "Female",
    "Introduction": "ac consequat metus sapien ut nunc vestibulum ante ipsum primis in faucibus orci luctus et ultrices posuere cubilia curae mauris",
    "KnownAs": "Alene"
  }, {
    "Usename": "wgiacubbo2p",
    "Email": "wmcgillacoell2p@senate.gov",
    "Avatar": "https://robohash.org/evenietquisquamet.png?size=100x100&set=set1",
    "City": "Samaro",
    "DateOfBirth": "2002-08-20T09:21:19Z",
    "Gender": "Male",
    "Introduction": "convallis duis consequat dui nec nisi volutpat eleifend donec ut dolor morbi vel lectus in quam",
    "KnownAs": "Wilmar"
  }, {
    "Usename": "nlinny2q",
    "Email": "nlehrer2q@purevolume.com",
    "Avatar": "https://robohash.org/exercitationemvelharum.png?size=100x100&set=set1",
    "City": "Vegachí",
    "DateOfBirth": "1997-03-31T02:55:05Z",
    "Gender": "Female",
    "Introduction": "quisque ut erat curabitur gravida nisi at nibh in hac habitasse platea dictumst aliquam",
    "KnownAs": "Nyssa"
  }, {
    "Usename": "racland2r",
    "Email": "rroofe2r@blog.com",
    "Avatar": "https://robohash.org/utdistinctiocum.png?size=100x100&set=set1",
    "City": "Karangbalong",
    "DateOfBirth": "2009-01-20T17:22:05Z",
    "Gender": "Male",
    "Introduction": "pharetra magna ac consequat metus sapien ut nunc vestibulum ante ipsum primis in faucibus orci",
    "KnownAs": "Reagen"
  }]